setup.py
mgmarkdown/__init__.py
mgmarkdown/css.py
mgmarkdown/pelican_mathjax_markdown_extension.py
mgmarkdown.egg-info/PKG-INFO
mgmarkdown.egg-info/SOURCES.txt
mgmarkdown.egg-info/dependency_links.txt
mgmarkdown.egg-info/entry_points.txt
mgmarkdown.egg-info/top_level.txt