Metadata-Version: 1.0
Name: mgmarkdown
Version: 1.1.0
Summary: Markdown converter with personal extensions
Home-page: https://github.com/goerz/mgmarkdown
Author: Michael Goerz
Author-email: mail@michaelgoerz.net
License: GPL
Platform: UNKNOWN
